kafka_connect_api/__init__.py
kafka_connect_api/aws_lambdas.py
kafka_connect_api/errors.py
kafka_connect_api/kafka_connect_api.py
kafka_connect_api/tools.py
kafka_connect_api-0.5.10.dist-info/LICENSE
kafka_connect_api-0.5.10.dist-info/METADATA
kafka_connect_api-0.5.10.dist-info/WHEEL
kafka_connect_api-0.5.10.dist-info/RECORD
