Metadata-Version: 2.1
Name: kafka_connect_api
Version: 0.5.10
Summary: Apache Kafka Connect client
License: MPL-2.0
Author: John Preston
Author-email: john@compose-x.io
Requires-Python: >=3.10,<4.0
Classifier: Development Status :: 4 - Beta
Classifier: Intended Audience :: Information Technology
Classifier: Intended Audience :: System Administrators
Classifier: License :: OSI Approved
Classifier: License :: OSI Approved :: Mozilla Public License 2.0 (MPL 2.0)
Classifier: Natural Language :: English
Classifier: Programming Language :: Python :: 3
Classifier: Programming Language :: Python :: 3.10
Classifier: Programming Language :: Python :: 3.11
Classifier: Programming Language :: Python :: 3.12
Classifier: Programming Language :: Python :: 3.13
Provides-Extra: awslambda
Requires-Dist: jsonschema (>=4.3.0,<5.0.0) ; extra == "awslambda"
Requires-Dist: requests (>=2.31.0,<3.0.0)
